vibetrimleft/__init__.py
vibetrimleft/ai.py
vibetrimleft/py.typed
vibetrimleft-0.1.0.dist-info/METADATA
vibetrimleft-0.1.0.dist-info/WHEEL
vibetrimleft-0.1.0.dist-info/licenses/LICENSE
vibetrimleft-0.1.0.dist-info/RECORD
